toughanimator/__init__.py
toughanimator/run.py
toughanimator/tough_classes.py
toughanimator-0.1.12.dist-info/METADATA
toughanimator-0.1.12.dist-info/WHEEL
toughanimator-0.1.12.dist-info/top_level.txt
toughanimator-0.1.12.dist-info/RECORD
