Metadata-Version: 2.4
Name: toughanimator
Version: 0.1.12
Summary: A tool for visualizing TOUGH simulation outputs.
Home-page: https://github.com/scarletref/toughanimator
Author: scarletref
Author-email: scarletreflection@gmail.com
Classifier: Programming Language :: Python :: 3
Classifier: License :: OSI Approved :: MIT License
Classifier: Operating System :: OS Independent
Requires-Python: >=3.11,<3.14
Requires-Dist: numpy
Requires-Dist: pandas
Requires-Dist: vtk
Dynamic: author
Dynamic: author-email
Dynamic: classifier
Dynamic: description
Dynamic: description-content-type
Dynamic: home-page
Dynamic: requires-dist
Dynamic: requires-python
Dynamic: summary
